LICENSE.md
MANIFEST.in
Makefile
NEWS
README.md
pyproject.toml
setup.py
.reuse/dep5
LICENSES/GFDL-1.3-or-later.txt
LICENSES/GPL-2.0-or-later.txt
doc/Makefile
doc/conf.py
doc/connect.rst
doc/ctrlrange.png
doc/engine.rst
doc/event.rst
doc/eventflow.png
doc/extra-units.rst
doc/extra.rst
doc/index.rst
doc/main.rst
doc/misc.rst
doc/patch.png
doc/start.rst
doc/tools.rst
doc/units.rst
doc/util.rst
doc/velocity.png
doc/velocityslope.png
doc/examples/aeolus.py
doc/examples/hooks.py
doc/examples/klick.py
doc/examples/output.py
doc/examples/process.py
doc/examples/process_file.py
doc/examples/router.py
doc/examples/skeleton.py
doc/man/Makefile
doc/man/livedings.1
doc/man/livedings.scd
doc/man/mididings.1
doc/man/mididings.scd
doc/man/reproducible-man.sh
doc/man/send_midi.1
doc/man/send_midi.scd
doc/templates/localtoc.html
doc/theme/nasophon/theme.conf
doc/theme/nasophon/static/nasophon.css
mididings/__init__.py
mididings/arguments.py
mididings/constants.py
mididings/engine.py
mididings/event.py
mididings/misc.py
mididings/overload.py
mididings/patch.py
mididings/scene.py
mididings/setup.py
mididings/unitrepr.py
mididings/util.py
mididings.egg-info/PKG-INFO
mididings.egg-info/SOURCES.txt
mididings.egg-info/dependency_links.txt
mididings.egg-info/requires.txt
mididings.egg-info/top_level.txt
mididings/extra/__init__.py
mididings/extra/ctrl_sysex.py
mididings/extra/dbus.py
mididings/extra/engine.py
mididings/extra/floating_split.py
mididings/extra/gm.py
mididings/extra/harmonizer.py
mididings/extra/inotify.py
mididings/extra/key_color.py
mididings/extra/latch.py
mididings/extra/memorize_scene.py
mididings/extra/osc.py
mididings/extra/panic.py
mididings/extra/pedal_noteoff.py
mididings/extra/per_channel.py
mididings/extra/polyphony.py
mididings/extra/suppress_pc.py
mididings/extra/voices.py
mididings/live/__init__.py
mididings/live/livedings.py
mididings/live/osc_control.py
mididings/live/widgets.py
mididings/units/__init__.py
mididings/units/base.py
mididings/units/call.py
mididings/units/engine.py
mididings/units/filters.py
mididings/units/generators.py
mididings/units/init.py
mididings/units/modifiers.py
mididings/units/printing.py
