Metadata-Version: 2.1
Name: mididings
Version: 20230111
Summary: A MIDI router/processor
Author-email: Dominic Sacré <dominic.sacre@gmx.de>
Maintainer-email: George Rawlinson <george@rawlinson.net.nz>
License: # Licenses
Project-URL: homepage, https://github.com/mididings/mididings
Project-URL: documentation, https://mididings.github.io/mididings/
Classifier: Topic :: Multimedia :: Sound/Audio :: MIDI
Classifier: Programming Language :: Python :: 3
Classifier: License :: OSI Approved :: GNU General Public License v2 or later (GPLv2+)
Classifier: License :: OSI Approved :: GNU Free Documentation License (FDL)
Classifier: Development Status :: 5 - Production/Stable
Requires-Python: >=3.7
Provides-Extra: osc
Provides-Extra: smf
Provides-Extra: autorestart
Provides-Extra: dbus
Provides-Extra: xdg
Provides-Extra: doc
Provides-Extra: test
License-File: LICENSE.md
